{
  "project_info": {
    "project_number": "992160753680",
    "firebase_url": "https://nerdslot-x.firebaseio.com",
    "project_id": "nerdslot-x",
    "storage_bucket": "nerdslot-x.appspot.com"
  },
  "client": [
    {
      "client_info": {
        "mobilesdk_app_id": "1:992160753680:android:ab429f3f29f26c00",
        "android_client_info": {
          "package_name": "org.nerdslot"
        }
      },
      "oauth_client": [
        {
          "client_id": "992160753680-pdo4a3hpp4g9816pu79l4bhtqps8e8v9.apps.googleusercontent.com",
          "client_type": 1,
          "android_info": {
            "package_name": "org.nerdslot",
            "certificate_hash": "642d4d4e8b5b744ead93b58b23fb9a1c80925b8b"
          }
        },
        {
          "client_id": "992160753680-f6pjtdna83950j764fae1hs822d7ujkd.apps.googleusercontent.com",
          "client_type": 3
        }
      ],
      "api_key": [
        {
          "current_key": "AIzaSyALv3NcZsTY8GDfa0CrB6QmJLpPo9Kteaw"
        }
      ],
      "services": {
        "appinvite_service": {
          "other_platform_oauth_client": [
            {
              "client_id": "992160753680-f6pjtdna83950j764fae1hs822d7ujkd.apps.googleusercontent.com",
              "client_type": 3
            }
          ]
        }
      }
    }
  ],
  "configuration_version": "1"
}